contextualMAB/Thompson.py
contextualMAB/UCB.py
contextualMAB/__init__.py
contextualMAB/contextualMAB.py
contextualMAB/eGreedy.py
contextualMAB/linThompson.py
contextualMAB/linUCB.py
contextualMAB/test.py
contextualMAB/utilMAB.py
contextualMAB-0.3.dist-info/LICENSES.txt
contextualMAB-0.3.dist-info/METADATA
contextualMAB-0.3.dist-info/WHEEL
contextualMAB-0.3.dist-info/top_level.txt
contextualMAB-0.3.dist-info/RECORD
